{"_default": {"1": {"id": 0, "fullname": "Architecture and Engineering"}, "2": {"id": 1, "fullname": "Arts and Design"}, "3": {"id": 2, "fullname": "Building and Grounds Cleaning"}, "4": {"id": 3, "fullname": "Business and Financial"}, "5": {"id": 4, "fullname": "Community and Social Service"}, "6": {"id": 5, "fullname": "Computer and Information Technology"}, "7": {"id": 6, "fullname": "Construction and Extraction"}, "8": {"id": 7, "fullname": "Education, Training, and Library"}, "9": {"id": 8, "fullname": "Entertainment and Sports"}, "10": {"id": 9, "fullname": "Farming, Fishing, and Forestry"}, "11": {"id": 10, "fullname": "Food Preparation and Serving"}, "12": {"id": 11, "fullname": "Healthcare"}, "13": {"id": 12, "fullname": "Installation, Maintenance, and Repair"}, "14": {"id": 13, "fullname": "Legal"}, "15": {"id": 14, "fullname": "Life, Physical, and Social Science"}, "16": {"id": 15, "fullname": "Management"}, "17": {"id": 16, "fullname": "Math"}, "18": {"id": 17, "fullname": "Media and Communication"}, "19": {"id": 18, "fullname": "Military"}, "20": {"id": 19, "fullname": "Office and Administrative Support"}, "21": {"id": 20, "fullname": "Personal Care and Service"}, "22": {"id": 21, "fullname": "Production"}, "23": {"id": 22, "fullname": "Protective Service"}, "24": {"id": 23, "fullname": "Sales"}, "25": {"id": 24, "fullname": "Transportation and Material Moving"}}}